text_rec_metric/__init__.py
text_rec_metric/main.py
text_rec_metric-0.0.1.dist-info/LICENSE
text_rec_metric-0.0.1.dist-info/METADATA
text_rec_metric-0.0.1.dist-info/WHEEL
text_rec_metric-0.0.1.dist-info/entry_points.txt
text_rec_metric-0.0.1.dist-info/top_level.txt
text_rec_metric-0.0.1.dist-info/RECORD
